{
  "ok": true,
  "data": {
    "version": 1,
    "title": "Legacy builder",
    "assets": [
      {
        "id": "1",
        "name": "Millenial Falcon",
        "thumbnail": "https://market.decentraland.org/static/media/logo.b7751b3e.svg",
        "url": "http://example.com",
        "tags": ["space", "ship"],
        "category": "space",
        "variations": []
      },
      {
        "id": "2",
        "name": "USS Drake",
        "thumbnail": "https://market.decentraland.org/static/media/logo.b7751b3e.svg",
        "url": "http://example.com",
        "tags": ["space", "ship"],
        "category": "space",
        "variations": []
      },
      {
        "id": "3",
        "name": "Tree",
        "thumbnail": "https://market.decentraland.org/static/media/logo.b7751b3e.svg",
        "url": "http://example.com",
        "tags": ["forest", "grass"],
        "category": "forest",
        "variations": []
      },
      {
        "id": "4",
        "name": "Building",
        "thumbnail": "https://market.decentraland.org/static/media/logo.b7751b3e.svg",
        "url": "http://example.com",
        "tags": ["city", "urban"],
        "category": "city",
        "variations": []
      }
    ]
  }
}
